tiktok_autoupload/__init__.py
tiktok_autoupload/uploader.py
tiktok_autoupload-1.0.2.dist-info/LICENSE
tiktok_autoupload-1.0.2.dist-info/METADATA
tiktok_autoupload-1.0.2.dist-info/WHEEL
tiktok_autoupload-1.0.2.dist-info/top_level.txt
tiktok_autoupload-1.0.2.dist-info/RECORD
