Metadata-Version: 2.1
Name: tiktok-autoupload
Version: 1.0.2
Summary: Python library to upload a video on tiktok using selenium
Author: Christian Fiore
License: GNU GENERAL PUBLIC LICENSE
Project-URL: Homepage, https://github.com/agente3z/tiktok-autoupload
License-File: LICENSE
Requires-Dist: selenium
Requires-Dist: selenium-stealth
